fixedpointmath/__init__.py
fixedpointmath/errors.py
fixedpointmath/fixed_point.py
fixedpointmath/fixed_point_integer_math.py
fixedpointmath/fixed_point_math.py
fixedpointmath-0.2.1.dist-info/WHEEL
fixedpointmath-0.2.1.dist-info/METADATA
fixedpointmath-0.2.1.dist-info/RECORD
