Metadata-Version: 2.1
Name: fixedpointmath
Version: 0.2.1
Summary: Fixed-point arithmetic and type that mirrors popular Solidity implementations
Author-email: Dylan Paiton <dylan@delv.tech>, Mihai Cosma <mihai@delv.tech>, Matthew Brown <matt@delv.tech>, Sheng Lundquist <sheng@delv.tech>
Requires-Python: >=3.8, <3.12
Classifier: Programming Language :: Python :: 3
Classifier: License :: OSI Approved :: Apache Software License
Classifier: Operating System :: OS Independent
Project-URL: Bug Tracker, https://github.com/delvtech/fixedpointmath/issues
Project-URL: Homepage, https://github.com/delvtech/fixedpointmath
